wehaveatogether/__init__.py
wehaveatogether/eastcoastplan.py
wehaveatogether-0.1.7.dist-info/METADATA
wehaveatogether-0.1.7.dist-info/WHEEL
wehaveatogether-0.1.7.dist-info/top_level.txt
wehaveatogether-0.1.7.dist-info/RECORD
