Metadata-Version: 2.4
Name: wehaveatogether
Version: 0.1.7
Summary: Short description of your package
Author: wehaveatogether
Classifier: Programming Language :: Python :: 3
Classifier: License :: OSI Approved :: MIT License
Requires-Python: >=3.6
Dynamic: author
Dynamic: classifier
Dynamic: description-content-type
Dynamic: requires-python
Dynamic: summary
